{
    "metadata": {
        "name": "Floating Social Icons with Theme Switch",
        "type": "UI Components",
        "category": "socials",
        "image": "assets/previewImages/socialsPreview/socials-4.png",
        "description": "Circular social media links with floating hover effect, dual theme support, and smooth transitions using CSS variables.",
        "version": "1.0",
        "author": "Admin",
        "date": "2025-03-03"
    },
    "style": "/* Reset */\n*,\n*::before,\n*::after {\n\tbox-sizing: border-box;\n\tmargin: 0;\n\tpadding: 0;\n}\n\n/* Default (light) theme variables */\n:root {\n\t--bg-color: #fff;\n\t--text-color: #333;\n\t--primary-color: #007bff;\n\t--icon-bg: #e9ecef;\n\t--icon-color: #333;\n\t--icon-hover-bg: var(--primary-color);\n\t--icon-hover-color: #fff;\n\t--toggle-bg: #e9ecef;\n\t--toggle-color: #333;\n\t--toggle-hover-bg: var(--primary-color);\n\t--toggle-hover-color: #fff;\n}\n\n/* Dark theme overrides */\n.dark-mode {\n\t--bg-color: #222;\n\t--text-color: #f5f5f5;\n\t--primary-color: #66b2ff;\n\t--icon-bg: #333;\n\t--icon-color: #f5f5f5;\n\t--icon-hover-bg: var(--primary-color);\n\t--icon-hover-color: #222;\n\t--toggle-bg: #333;\n\t--toggle-color: #f5f5f5;\n\t--toggle-hover-bg: var(--primary-color);\n\t--toggle-hover-color: #222;\n}\n\nbody {\n\tbackground-color: var(--bg-color);\n\tcolor: var(--text-color);\n\tfont-family: \"Segoe UI\", Tahoma, Geneva, Verdana, sans-serif;\n\tdisplay: flex;\n\tflex-direction: column;\n\talign-items: center;\n\tjustify-content: center;\n\tmin-height: 100vh;\n\ttransition: background-color 0.3s, color 0.3s;\n\tpadding: 20px;\n}\n\n/* Social icons container */\n.social-container {\n\tdisplay: flex;\n\tgap: 20px;\n\tpadding: 20px;\n}\n\n.social-container a {\n\tdisplay: flex;\n\talign-items: center;\n\tjustify-content: center;\n\twidth: 70px;\n\theight: 70px;\n\tbackground-color: var(--icon-bg);\n\tborder-radius: 50%;\n\tfont-size: 28px;\n\tcolor: var(--icon-color);\n\ttext-decoration: none;\n\ttransition: background-color 0.3s, color 0.3s, transform 0.3s;\n\tbox-shadow: 0 4px 6px rgba(0, 0, 0, 0.1);\n}\n\n.social-container a:hover {\n\tbackground-color: var(--icon-hover-bg);\n\tcolor: var(--icon-hover-color);\n\ttransform: translateY(-5px);\n}\n\n/* Floating theme toggle button */\n.theme-toggle {\n\tposition: fixed;\n\tbottom: 20px;\n\tright: 20px;\n\tpadding: 10px 15px;\n\tbackground-color: var(--toggle-bg);\n\tcolor: var(--toggle-color);\n\tborder: none;\n\tborder-radius: 5px;\n\tcursor: pointer;\n\ttransition: background-color 0.3s, color 0.3s;\n}\n\n.theme-toggle:hover {\n\tbackground-color: var(--toggle-hover-bg);\n\tcolor: var(--toggle-hover-color);\n}\n\n/* Responsive adjustments */\n@media (max-width: 600px) {\n\t.social-container {\n\t\tgap: 15px;\n\t}\n\t.social-container a {\n\t\twidth: 60px;\n\t\theight: 60px;\n\t\tfont-size: 24px;\n\t}\n}\n",
    "html": "<link rel=\"stylesheet\" href=\"https://cdn.jsdelivr.net/npm/@fortawesome/fontawesome-free@6.4.0/css/all.min.css\" />\n<div class=\"social-container\">\n\t<a href=\"https://facebook.com\" target=\"_blank\" aria-label=\"Facebook\"><i class=\"fab fa-facebook-f\"></i></a>\n\t<a href=\"https://twitter.com\" target=\"_blank\" aria-label=\"Twitter\"><i class=\"fab fa-twitter\"></i></a>\n\t<a href=\"https://instagram.com\" target=\"_blank\" aria-label=\"Instagram\"><i class=\"fab fa-instagram\"></i></a>\n\t<a href=\"https://linkedin.com\" target=\"_blank\" aria-label=\"LinkedIn\"><i class=\"fab fa-linkedin-in\"></i></a>\n\t<a href=\"https://github.com\" target=\"_blank\" aria-label=\"GitHub\"><i class=\"fab fa-github\"></i></a>\n</div>\n<button class=\"theme-toggle\" id=\"themeToggleBtn\">Toggle Theme</button>",
    "script": "const themeToggleBtn = document.getElementById(\"themeToggleBtn\");\nthemeToggleBtn.addEventListener(\"click\", () => {\n\tdocument.body.classList.toggle(\"dark-mode\");\n});\n"
}